_treiber.cpython-36m-x86_64-linux-gnu.so
cassie/treiber_stack.py
cassie/__init__.py
cassie-0.1.1.dist-info/WHEEL
cassie-0.1.1.dist-info/top_level.txt
cassie-0.1.1.dist-info/METADATA
cassie-0.1.1.dist-info/RECORD
