Metadata-Version: 1.1
Name: cassie
Version: 0.1.1
Summary: Concurrency utilities for python.
Home-page: https://github.com/IanTayler/cassie
Author: Ian Tayler
Author-email: iangtayler@gmail.com
License: MIT License
Platform: UNKNOWN
Classifier: Intended Audience :: Developers
Classifier: License :: OSI Approved :: MIT License
Classifier: Programming Language :: Python :: 3
Classifier: Programming Language :: Python :: 3.6
Classifier: Programming Language :: Python :: 3.7
